fulladder/fullAdder.v
module FullAdder(X, Y, Cin, S, Cout);
input X, Y, Cin;
output S, Cout;

assign S = X ^ Y ^ Cin;
assign Cout = (X & Y) | (Y & Cin) | (X & Cin);

endmodule

fulladder/fullAdder_tb.v
module FullAdder_tb;
reg X, Y, Cin;
wire S, Cout;

FullAdder FA(X, Y, Cin, S, Cout);
initial
begin
$dumpfile("FA.vcd");
$dumpvars(0, FullAdder_tb);
$monitor($time, "X = %b, Y = %b, Cin = %b, S = %b, Cout=%b", X, Y, Cin, S, Cout);

#5 X = 0; Y = 0; Cin = 0;
#5 X = 0; Y = 0; Cin = 1;
#5 X = 0; Y = 1; Cin = 0;
#5 X = 0; Y = 1; Cin = 1;
#5 X = 1; Y = 0; Cin = 0;
#5 X = 1; Y = 0; Cin = 1;
#5 X = 1; Y = 1; Cin = 0;
#5 X = 1; Y = 1; Cin = 1;
#5 $finish;

end 
endmodule

fulladder/FA.vcd
$date
	Fri Aug 15 17:54:40 2025
$end
$version
	Icarus Verilog
$end
$timescale
	1s
$end
$scope module FullAdder_tb $end
$var wire 1 ! S $end
$var wire 1 " Cout $end
$var reg 1 # Cin $end
$var reg 1 $ X $end
$var reg 1 % Y $end
$scope module FA $end
$var wire 1 # Cin $end
$var wire 1 " Cout $end
$var wire 1 ! S $end
$var wire 1 $ X $end
$var wire 1 % Y $end
$upscope $end
$upscope $end
$enddefinitions $end
$comment Show the parameter values. $end
$dumpall
$end
#0
$dumpvars
x%
x$
x#
x"
x!
$end
#5
0"
0!
0#
0%
0$
#10
1!
1#
#15
0#
1%
#20
1"
0!
1#
#25
0"
1!
0#
0%
1$
#30
1"
0!
1#
#35
0#
1%
#40
1!
1#
